uyeia/__init__.py
uyeia/cache.py
uyeia/errors_cache.db
uyeia/exceptions.py
uyeia/serializers.py
uyeia/type.py
uyeia/uyeia.errors.json
uyeia-1.0.1.dist-info/METADATA
uyeia-1.0.1.dist-info/WHEEL
uyeia-1.0.1.dist-info/RECORD
