Metadata-Version: 2.4
Name: uyeia
Version: 1.0.1
Summary: Add your description here
Author-email: dair <d.aires@easi.net>
Requires-Python: >=3.8
